prompt_unifier/__init__.py
prompt_unifier/ai/__init__.py
prompt_unifier/ai/executor.py
prompt_unifier/cli/__init__.py
prompt_unifier/cli/commands.py
prompt_unifier/cli/helpers.py
prompt_unifier/cli/main.py
prompt_unifier/config/__init__.py
prompt_unifier/config/manager.py
prompt_unifier/constants.py
prompt_unifier/core/__init__.py
prompt_unifier/core/batch_validator.py
prompt_unifier/core/content_parser.py
prompt_unifier/core/encoding.py
prompt_unifier/core/functional_test_parser.py
prompt_unifier/core/functional_validator.py
prompt_unifier/core/scaff_validator.py
prompt_unifier/core/separator.py
prompt_unifier/core/validator.py
prompt_unifier/core/yaml_parser.py
prompt_unifier/git/__init__.py
prompt_unifier/git/service.py
prompt_unifier/handlers/__init__.py
prompt_unifier/handlers/base_handler.py
prompt_unifier/handlers/continue_handler.py
prompt_unifier/handlers/handler_utils.py
prompt_unifier/handlers/kilo_code_handler.py
prompt_unifier/handlers/protocol.py
prompt_unifier/handlers/registry.py
prompt_unifier/models/__init__.py
prompt_unifier/models/functional_test.py
prompt_unifier/models/git_config.py
prompt_unifier/models/prompt.py
prompt_unifier/models/rule.py
prompt_unifier/models/scaff.py
prompt_unifier/models/validation.py
prompt_unifier/output/__init__.py
prompt_unifier/output/json_formatter.py
prompt_unifier/output/rich_formatter.py
prompt_unifier/output/rich_table_formatter.py
prompt_unifier/utils/__init__.py
prompt_unifier/utils/excerpt.py
prompt_unifier/utils/file_scanner.py
prompt_unifier/utils/formatting.py
prompt_unifier/utils/logging_config.py
prompt_unifier/utils/path_filter.py
prompt_unifier/utils/path_helpers.py
prompt_unifier/utils/repo_metadata.py
prompt_unifier-2.5.0.dist-info/METADATA
prompt_unifier-2.5.0.dist-info/WHEEL
prompt_unifier-2.5.0.dist-info/entry_points.txt
prompt_unifier-2.5.0.dist-info/licenses/LICENSE
prompt_unifier-2.5.0.dist-info/RECORD
