Metadata-Version: 2.4
Name: prompt-unifier
Version: 2.5.0
Summary: CLI tool for managing AI prompt templates with YAML frontmatter
License: MIT
License-File: LICENSE
Keywords: cli,ai,prompts,yaml,templates,llm
Author: Waewoo
Author-email: waewoo@gmail.com
Requires-Python: >=3.11,<4.0
Classifier: Development Status :: 4 - Beta
Classifier: Environment :: Console
Classifier: Intended Audience :: Developers
Classifier: License :: OSI Approved :: MIT License
Classifier: Programming Language :: Python :: 3
Classifier: Programming Language :: Python :: 3.11
Classifier: Programming Language :: Python :: 3.12
Classifier: Programming Language :: Python :: 3.13
Classifier: Programming Language :: Python :: 3.14
Classifier: Topic :: Software Development :: Libraries :: Python Modules
Classifier: Topic :: Text Processing :: Markup
Requires-Dist: gitpython (>=3.1.45,<4.0.0)
Requires-Dist: litellm (>=1.80.11,<2.0.0)
Requires-Dist: pydantic (>=2.12.4,<3.0.0)
Requires-Dist: python-dotenv (>=1.2.1,<2.0.0)
Requires-Dist: pyyaml (>=6.0.3,<7.0.0)
Requires-Dist: rich (>=14.2.0,<15.0.0)
Requires-Dist: typer (>=0.20.0,<0.21.0)
Project-URL: Bug Tracker, https://gitlab.com/waewoo/prompt-unifier/-/issues
Project-URL: Changelog, https://waewoo.gitlab.io/prompt-unifier/changelog/
Project-URL: Contributing, https://waewoo.gitlab.io/prompt-unifier/contributing/
Project-URL: Documentation, https://waewoo.gitlab.io/prompt-unifier/getting-started/
Project-URL: Homepage, https://waewoo.gitlab.io/prompt-unifier
Project-URL: Repository, https://gitlab.com/waewoo/prompt-unifier
Project-URL: ReleaseNotes, https://gitlab.com/waewoo/prompt-unifier/-/releases
